MANIFEST.in
distribute_setup.py
setup.py
lib/gevent_selfpipe/__init__.py
lib/gevent_selfpipe.egg-info/PKG-INFO
lib/gevent_selfpipe.egg-info/SOURCES.txt
lib/gevent_selfpipe.egg-info/dependency_links.txt
lib/gevent_selfpipe.egg-info/requires.txt
lib/gevent_selfpipe.egg-info/top_level.txt