Metadata-Version: 1.0
Name: gevent-selfpipe
Version: 0.0.3
Summary: Hack to enable gevent-based scheduling of blocking calls.
Home-page: http://github.com/zacharyvoase/gevent-selfpipe
Author: Zachary Voase
Author-email: z@zacharyvoase.com
License: UNKNOWN
Platform: UNKNOWN
